audiomaker/__init__.py
audiomaker/banner.py
audiomaker/cli.py
audiomaker/core.py
audiomaker/utils.py
audiomaker-1.0.0.dist-info/METADATA
audiomaker-1.0.0.dist-info/WHEEL
audiomaker-1.0.0.dist-info/entry_points.txt
audiomaker-1.0.0.dist-info/top_level.txt
audiomaker-1.0.0.dist-info/RECORD
