Metadata-Version: 2.4
Name: audiomaker
Version: 1.0.0
Summary: Unlimited text-to-speech generation with chunking and seamless merging
Home-page: https://github.com/AnkushRathour/AudioMaker
Author: Ankush Rathour
Author-email: ankush.14072000.rathour@gmail.com
License: MIT
Project-URL: Bug Tracker, https://github.com/AnkushRathour/AudioMaker/issues
Project-URL: Source, https://github.com/AnkushRathour/AudioMaker
Keywords: text-to-speech tts audio synthesis mp3 wav microsoft-edge
Classifier: Programming Language :: Python :: 3
Classifier: License :: OSI Approved :: MIT License
Classifier: Operating System :: OS Independent
Classifier: Topic :: Multimedia :: Sound/Audio :: Speech
Requires-Python: >=3.8
Requires-Dist: tqdm>=4.64.0
Requires-Dist: edge-tts>=6.1.9
Requires-Dist: pydub>=0.25.1
Dynamic: author
Dynamic: author-email
Dynamic: classifier
Dynamic: description
Dynamic: description-content-type
Dynamic: home-page
Dynamic: keywords
Dynamic: license
Dynamic: project-url
Dynamic: requires-dist
Dynamic: requires-python
Dynamic: summary
